birankpy/__init__.py
birankpy-1.0.1.dist-info/LICENSE
birankpy-1.0.1.dist-info/LICENSE.md
birankpy-1.0.1.dist-info/METADATA
birankpy-1.0.1.dist-info/WHEEL
birankpy-1.0.1.dist-info/top_level.txt
birankpy-1.0.1.dist-info/RECORD
