Metadata-Version: 2.1
Name: birankpy
Version: 1.0.1
Summary: Ranking nodes in bipartite networks with efficiency and flexibility
Home-page: https://github.com/BrianAronson/birankr
Author: Kaicheng Yang
Author-email: yangkc@iu.edu
License: MIT
Platform: UNKNOWN
Requires-Dist: networkx (>=2.5)
Requires-Dist: pandas (>=0.23.4)
Requires-Dist: numpy (>=1.16.2)
Requires-Dist: scipy (>=1.2.0)
